<metadata xml:lang="en"><Esri><CreaDate>20120503</CreaDate><CreaTime>12065800</CreaTime><ArcGISFormat>1.0</ArcGISFormat><SyncOnce>FALSE</SyncOnce><ModDate>20130824</ModDate><ModTime>17333200</ModTime><ArcGISProfile>ItemDescription</ArcGISProfile><DataProperties><itemProps><itemName Sync="TRUE">pres_2013_precincts</itemName><imsContentType Sync="TRUE">002</imsContentType><itemLocation><linkage Sync="TRUE">file://\\DATOCRRC-PC\D$\Dropbox\NDI\2013pres\Presidential_2013_shp\asd\precinct_presidential_2013\pres_2013_precincts.shp</linkage><protocol Sync="TRUE">Local Area Network</protocol></itemLocation><itemSize Sync="TRUE">0.000</itemSize></itemProps><coordRef><type Sync="TRUE">Projected</type><geogcsn Sync="TRUE">GCS_WGS_1984</geogcsn><projcsn Sync="TRUE">TM_Georgia38</projcsn><peXml Sync="TRUE">&lt;ProjectedCoordinateSystem xsi:type='typens:ProjectedCoordinateSystem' xmlns:xsi='http://www.w3.org/2001/XMLSchema-instance' xmlns:xs='http://www.w3.org/2001/XMLSchema' xmlns:typens='http://www.esri.com/schemas/ArcGIS/10.0'&gt;&lt;WKT&gt;PROJCS[&amp;quot;TM_Georgia38&amp;quot;,GEOGCS[&amp;quot;GCS_WGS_1984&amp;quot;,DATUM[&amp;quot;D_WGS_1984&amp;quot;,SPHEROID[&amp;quot;WGS_1984&amp;quot;,6378137.0,298.257223563]],PRIMEM[&amp;quot;Greenwich&amp;quot;,0.0],UNIT[&amp;quot;Degree&amp;quot;,0.0174532925199433]],PROJECTION[&amp;quot;Transverse_Mercator&amp;quot;],PARAMETER[&amp;quot;False_Easting&amp;quot;,500000.0],PARAMETER[&amp;quot;False_Northing&amp;quot;,0.0],PARAMETER[&amp;quot;Central_Meridian&amp;quot;,45.0],PARAMETER[&amp;quot;Scale_Factor&amp;quot;,0.9996],PARAMETER[&amp;quot;Latitude_Of_Origin&amp;quot;,0.0],UNIT[&amp;quot;Meter&amp;quot;,1.0]]&lt;/WKT&gt;&lt;XOrigin&gt;-5120900&lt;/XOrigin&gt;&lt;YOrigin&gt;-9998100&lt;/YOrigin&gt;&lt;XYScale&gt;450445547.3910538&lt;/XYScale&gt;&lt;ZOrigin&gt;-100000&lt;/ZOrigin&gt;&lt;ZScale&gt;10000&lt;/ZScale&gt;&lt;MOrigin&gt;-100000&lt;/MOrigin&gt;&lt;MScale&gt;10000&lt;/MScale&gt;&lt;XYTolerance&gt;0.001&lt;/XYTolerance&gt;&lt;ZTolerance&gt;0.001&lt;/ZTolerance&gt;&lt;MTolerance&gt;0.001&lt;/MTolerance&gt;&lt;HighPrecision&gt;true&lt;/HighPrecision&gt;&lt;/ProjectedCoordinateSystem&gt;</peXml></coordRef><lineage><Process ToolSource="C:\Program Files\ArcGIS\Desktop10.0\ArcToolbox\Toolboxes\Conversion Tools.tbx\FeatureClassToFeatureClass" Date="20120905" Time="182254">FeatureClassToFeatureClass "D:\My Projects\Elections DB\Release\geography\local_elections_2010\local_precinct_2010.shp" C:\Users\d.sichinava\Dropbox\NDI\2012parl\2012_parl.mdb local_2010_precincts # "Region_EN "Region_EN" true true false 254 Text 0 0 ,First,#,D:\My Projects\Elections DB\Release\geography\local_elections_2010\local_precinct_2010.shp,Region_EN,-1,-1;Region_KA "Region_KA" true true false 254 Text 0 0 ,First,#,D:\My Projects\Elections DB\Release\geography\local_elections_2010\local_precinct_2010.shp,Region_KA,-1,-1;District_E "District_E" true true false 254 Text 0 0 ,First,#,D:\My Projects\Elections DB\Release\geography\local_elections_2010\local_precinct_2010.shp,District_E,-1,-1;District_K "District_K" true true false 254 Text 0 0 ,First,#,D:\My Projects\Elections DB\Release\geography\local_elections_2010\local_precinct_2010.shp,District_K,-1,-1;Precinct_i "Precinct_i" true true false 16 Double 6 15 ,First,#,D:\My Projects\Elections DB\Release\geography\local_elections_2010\local_precinct_2010.shp,Precinct_i,-1,-1;District_c "District_c" true true false 16 Double 6 15 ,First,#,D:\My Projects\Elections DB\Release\geography\local_elections_2010\local_precinct_2010.shp,District_c,-1,-1;Precinct_c "Precinct_c" true true false 16 Double 6 15 ,First,#,D:\My Projects\Elections DB\Release\geography\local_elections_2010\local_precinct_2010.shp,Precinct_c,-1,-1;Total_vote "Total_vote" true true false 16 Double 6 15 ,First,#,D:\My Projects\Elections DB\Release\geography\local_elections_2010\local_precinct_2010.shp,Total_vote,-1,-1;Turnout_12 "Turnout_12" true true false 16 Double 6 15 ,First,#,D:\My Projects\Elections DB\Release\geography\local_elections_2010\local_precinct_2010.shp,Turnout_12,-1,-1;Turnout_5p "Turnout_5p" true true false 16 Double 6 15 ,First,#,D:\My Projects\Elections DB\Release\geography\local_elections_2010\local_precinct_2010.shp,Turnout_5p,-1,-1;Turnout_8p "Turnout_8p" true true false 16 Double 6 15 ,First,#,D:\My Projects\Elections DB\Release\geography\local_elections_2010\local_precinct_2010.shp,Turnout_8p,-1,-1;biul_bat "biul_bat" true true false 16 Double 6 15 ,First,#,D:\My Projects\Elections DB\Release\geography\local_elections_2010\local_precinct_2010.shp,biul_bat,-1,-1;All_for_Ge "All_for_Ge" true true false 16 Double 6 15 ,First,#,D:\My Projects\Elections DB\Release\geography\local_elections_2010\local_precinct_2010.shp,All_for_Ge,-1,-1;Topadze_in "Topadze_in" true true false 16 Double 6 15 ,First,#,D:\My Projects\Elections DB\Release\geography\local_elections_2010\local_precinct_2010.shp,Topadze_in,-1,-1;UNM "UNM" true true false 16 Double 6 15 ,First,#,D:\My Projects\Elections DB\Release\geography\local_elections_2010\local_precinct_2010.shp,UNM,-1,-1;Sportsmen "Sportsmen" true true false 16 Double 6 15 ,First,#,D:\My Projects\Elections DB\Release\geography\local_elections_2010\local_precinct_2010.shp,Sportsmen,-1,-1;National_c "National_c" true true false 16 Double 6 15 ,First,#,D:\My Projects\Elections DB\Release\geography\local_elections_2010\local_precinct_2010.shp,National_c,-1,-1;Radical_de "Radical_de" true true false 16 Double 6 15 ,First,#,D:\My Projects\Elections DB\Release\geography\local_elections_2010\local_precinct_2010.shp,Radical_de,-1,-1;CDM "CDM" true true false 16 Double 6 15 ,First,#,D:\My Projects\Elections DB\Release\geography\local_elections_2010\local_precinct_2010.shp,CDM,-1,-1;Our_countr "Our_countr" true true false 16 Double 6 15 ,First,#,D:\My Projects\Elections DB\Release\geography\local_elections_2010\local_precinct_2010.shp,Our_countr,-1,-1;Future_Geo "Future_Geo" true true false 16 Double 6 15 ,First,#,D:\My Projects\Elections DB\Release\geography\local_elections_2010\local_precinct_2010.shp,Future_Geo,-1,-1;Freedom_pa "Freedom_pa" true true false 16 Double 6 15 ,First,#,D:\My Projects\Elections DB\Release\geography\local_elections_2010\local_precinct_2010.shp,Freedom_pa,-1,-1;Future_par "Future_par" true true false 254 Text 0 0 ,First,#,D:\My Projects\Elections DB\Release\geography\local_elections_2010\local_precinct_2010.shp,Future_par,-1,-1;NDP "NDP" true true false 254 Text 0 0 ,First,#,D:\My Projects\Elections DB\Release\geography\local_elections_2010\local_precinct_2010.shp,NDP,-1,-1;Solidarity "Solidarity" true true false 16 Double 6 15 ,First,#,D:\My Projects\Elections DB\Release\geography\local_elections_2010\local_precinct_2010.shp,Solidarity,-1,-1;Mamulishvi "Mamulishvi" true true false 254 Text 0 0 ,First,#,D:\My Projects\Elections DB\Release\geography\local_elections_2010\local_precinct_2010.shp,Mamulishvi,-1,-1;Tortladze_ "Tortladze_" true true false 16 Double 6 15 ,First,#,D:\My Projects\Elections DB\Release\geography\local_elections_2010\local_precinct_2010.shp,Tortladze_,-1,-1;National_a "National_a" true true false 16 Double 6 15 ,First,#,D:\My Projects\Elections DB\Release\geography\local_elections_2010\local_precinct_2010.shp,National_a,-1,-1;Ivanishvil "Ivanishvil" true true false 16 Double 6 15 ,First,#,D:\My Projects\Elections DB\Release\geography\local_elections_2010\local_precinct_2010.shp,Ivanishvil,-1,-1;Alasania "Alasania" true true false 16 Double 6 15 ,First,#,D:\My Projects\Elections DB\Release\geography\local_elections_2010\local_precinct_2010.shp,Alasania,-1,-1;Topadze "Topadze" true true false 16 Double 6 15 ,First,#,D:\My Projects\Elections DB\Release\geography\local_elections_2010\local_precinct_2010.shp,Topadze,-1,-1;Ugulava "Ugulava" true true false 16 Double 6 15 ,First,#,D:\My Projects\Elections DB\Release\geography\local_elections_2010\local_precinct_2010.shp,Ugulava,-1,-1;Dzidziguri "Dzidziguri" true true false 16 Double 6 15 ,First,#,D:\My Projects\Elections DB\Release\geography\local_elections_2010\local_precinct_2010.shp,Dzidziguri,-1,-1;Chanturia "Chanturia" true true false 16 Double 6 15 ,First,#,D:\My Projects\Elections DB\Release\geography\local_elections_2010\local_precinct_2010.shp,Chanturia,-1,-1;Laghidze "Laghidze" true true false 16 Double 6 15 ,First,#,D:\My Projects\Elections DB\Release\geography\local_elections_2010\local_precinct_2010.shp,Laghidze,-1,-1;Vashadze "Vashadze" true true false 16 Double 6 15 ,First,#,D:\My Projects\Elections DB\Release\geography\local_elections_2010\local_precinct_2010.shp,Vashadze,-1,-1;Iakobidze "Iakobidze" true true false 16 Double 6 15 ,First,#,D:\My Projects\Elections DB\Release\geography\local_elections_2010\local_precinct_2010.shp,Iakobidze,-1,-1;N_Ivanishv "N_Ivanishv" true true false 16 Double 6 15 ,First,#,D:\My Projects\Elections DB\Release\geography\local_elections_2010\local_precinct_2010.shp,N_Ivanishv,-1,-1" #</Process><Process ToolSource="C:\Program Files\ArcGIS\Desktop10.0\ArcToolbox\Toolboxes\Data Management Tools.tbx\CalculateField" Date="20120911" Time="114214">CalculateField local_2010_precincts District [District_c] VB #</Process><Process ToolSource="C:\Program Files\ArcGIS\Desktop10.0\ArcToolbox\Toolboxes\Data Management Tools.tbx\CalculateField" Date="20120911" Time="114258">CalculateField local_2010_precincts District [District_c] VB #</Process><Process ToolSource="C:\Program Files\ArcGIS\Desktop10.0\ArcToolbox\Toolboxes\Data Management Tools.tbx\CalculateField" Date="20120911" Time="114318">CalculateField local_2010_precincts District [District_c] VB #</Process><Process ToolSource="C:\Program Files\ArcGIS\Desktop10.0\ArcToolbox\Toolboxes\Data Management Tools.tbx\CalculateField" Date="20120911" Time="200708">CalculateField local_2010_precincts PrecID "[District]*1000+ [PrecID]" VB #</Process><Process ToolSource="C:\Program Files\ArcGIS\Desktop10.0\ArcToolbox\Toolboxes\Data Management Tools.tbx\CalculateField" Date="20120911" Time="200744">CalculateField local_2010_precincts PrecID "[District]*1000+ [PrecID]" VB #</Process><Process ToolSource="C:\Program Files\ArcGIS\Desktop10.0\ArcToolbox\Toolboxes\Data Management Tools.tbx\CalculateField" Date="20120911" Time="202019">CalculateField local_2010_precincts PrecID "[PrecID]= [District]*1000+ [Precinct]" VB #</Process><Process ToolSource="C:\Program Files\ArcGIS\Desktop10.0\ArcToolbox\Toolboxes\Data Management Tools.tbx\CalculateField" Date="20120911" Time="202057">CalculateField local_2010_precincts PrecID "[District]*1000+ [Precinct]" VB #</Process><Process ToolSource="C:\Program Files (x86)\ArcGIS\Desktop10.0\ArcToolbox\Toolboxes\Data Management Tools.tbx\CalculateField" Date="20130824" Time="173014">CalculateField pres_2013_precincts PrecID "[District]*1000+ [Precinct]" VB #</Process><Process ToolSource="C:\Program Files (x86)\ArcGIS\Desktop10.0\ArcToolbox\Toolboxes\Conversion Tools.tbx\FeatureClassToFeatureClass" Date="20130824" Time="173335">FeatureClassToFeatureClass D:\Dropbox\NDI\2013pres\Data\2013_pres.mdb\pres_2013_precincts D:\Dropbox\NDI\2013pres\Presidential_2013_shp\asd\precinct_presidential_2013 pres_2013_precincts.shp # "Shape_Leng "Shape_Leng" false true true 8 Double 0 0 ,First,#,D:\Dropbox\NDI\2013pres\Data\2013_pres.mdb\pres_2013_precincts,Shape_Length,-1,-1;Shape_Area "Shape_Area" false true true 8 Double 0 0 ,First,#,D:\Dropbox\NDI\2013pres\Data\2013_pres.mdb\pres_2013_precincts,Shape_Area,-1,-1;District "District" true true false 4 Long 0 0 ,First,#,D:\Dropbox\NDI\2013pres\Data\2013_pres.mdb\pres_2013_precincts,District,-1,-1;Precinct "Precinct" true true false 4 Long 0 0 ,First,#,D:\Dropbox\NDI\2013pres\Data\2013_pres.mdb\pres_2013_precincts,Precinct,-1,-1;PrecID "PrecID" true true false 4 Float 0 0 ,First,#,D:\Dropbox\NDI\2013pres\Data\2013_pres.mdb\pres_2013_precincts,PrecID,-1,-1" #</Process></lineage></DataProperties><SyncDate>20130824</SyncDate><SyncTime>17333200</SyncTime></Esri><Binary><Thumbnail><Data EsriPropertyType="PictureX">/9j/4AAQSkZJRgABAQEAAQABAAD/2wBDAAgGBgcGBQgHBwcJCQgKDBQNDAsLDBkSEw8UHRofHh0a
HBwgJC4nICIsIxwcKDcpLDAxNDQ0Hyc5PTgyPC4zNDL/2wBDAQkJCQwLDBgNDRgyIRwhMjIyMjIy
MjIyMjIyMjIyMjIyMjIyMjIyMjIyMjIyMjIyMjIyMjIyMjIyMjIyMjIyMjL/wAARCACFAMgDASIA
AhEBAxEB/8QAHwAAAQUBAQEBAQEAAAAAAAAAAAECAwQFBgcICQoL/8QAtRAAAgEDAwIEAwUFBAQA
AAF9AQIDAAQRBRIhMUEGE1FhByJxFDKBkaEII0KxwRVS0fAkM2JyggkKFhcYGRolJicoKSo0NTY3
ODk6Q0RFRkdISUpTVFVWV1hZWmNkZWZnaGlqc3R1dnd4eXqDhIWGh4iJipKTlJWWl5iZmqKjpKWm
p6ipqrKztLW2t7i5usLDxMXGx8jJytLT1NXW19jZ2uHi4+Tl5ufo6erx8vP09fb3+Pn6/8QAHwEA
AwEBAQEBAQEBAQAAAAAAAAECAwQFBgcICQoL/8QAtREAAgECBAQDBAcFBAQAAQJ3AAECAxEEBSEx
BhJBUQdhcRMiMoEIFEKRobHBCSMzUvAVYnLRChYkNOEl8RcYGRomJygpKjU2Nzg5OkNERUZHSElK
U1RVVldYWVpjZGVmZ2hpanN0dXZ3eHl6goOEhYaHiImKkpOUlZaXmJmaoqOkpaanqKmqsrO0tba3
uLm6wsPExcbHyMnK0tPU1dbX2Nna4uPk5ebn6Onq8vP09fb3+Pn6/9oADAMBAAIRAxEAPwD3+iii
gAooooAKKKKACiiigAooooAKKKKACiiigAooooAKKKKACiiigAooooAKKKKACiiigAooooAKKKz7
wXIu1EDyssqHKAAgEY9eBnOKTdlcBZ9Xtba3mmkLARSGMgAklh/T36VmxeJAI5EuNizkExMFOxic
hR6ntyOOetBtXgeBBZSbjKXVhLznHTcBwMf1rWutPtr0Bp4h5gAw4+8uPf8AE1mpSkrrQZQTxNYl
442YK+WEoJ+5jAz7jkHjscnFaltdRXcZeIkgMVOf89xgj2IrMutBQw7LMRJkjcJAW3D0JznHt39a
pJHNBfky3BslHO2JcIMcAZIwQc5/wPWZVJQ1ktAtc6ais6xvQyhJZzIzOFRtmM/KDyQMDvWjWsZK
SuhBRRRVAFFFFABRRRQAUUUUAFFFFABRRRQAUUUUAFFFFABRRSMwVSzEAAZJPagBa59vFlrHeJA9
vOA5YAhckY55Hvyf88Ra74rtbKM29nMkl0x27gRtTrzk8Z4rj23Mu6USSSO/mdwTyuVyCNv0x6YG
CDWc52asM9TR0kQPGysjDIZTkGoLm0MziWKZ4ZhxuU5BHoV6HrXMaPrN7a7Le5iY2/BSRl/hIzjP
GDg559gO2erluI4upLN02qMn8h/nmmpxkrgYt29za3cYu7ppI5AQYo1HzAe+QF6479fYGrU+keXF
tsdoXayiOVyUGepHXH/165vU7u+u7r7RbTTIjORGjny93ZQPx6d854rQ07WpLeNxJ5lxluSZNxTp
kZ5568cdu54xc4O8ZbBqbtlZCCFfOCPLnOeoX0C56D2qK7+22zzXEcrPCcNs27ivABAHGRxnr3/O
nqGsrLbEW+REww8m3cQCM8KOSMZyfb8s251Ii8VbWSdsepdGAQAcluDuIAI29VPXtUqkFGyf3BY6
KHUoWjQSSIJS6xlVOfmIzV2s/THS8to7uWGIXXIchfmU9OvUcYrQraOwgpokQuUDqXHVc806ufvb
FVv1f93GwkMwnHytgggqcckcqMkjt6VNSfIr2Glc1brU7OykWO4nCM3QYJz7cDr7VZjkSVA8bBlP
QiuTlaRLmP8A18zhhESxXcMgnG7C9Bzkn0znituwuIraycO6YRjtEZ3bgeeO553fkfSsqddTlboD
Rp0VmxGK93yupf5iuxx9z2wf1qaCcxTLaysWLAmJjySB1B9xn/JpQxMJzcAcdLlyimiRCFIdSG6H
PWnV0iCiiigAooooAKKKKACsHxFBq17GbSyWMW0ifO/8YIJOBzgdv1reqjq1zDaWDTXF1JaxAgNL
GBkZOO4NJ7AebpYpCkU8jugdWML7CQOARjHuCAcd6tx2lxIXi2FYlICGYZ+b8uwDZ4I+U1o3FlJq
EE7qPtEMbiGOQg7lBUZxyQAD3x39hVNreaJGmtnaCGFynkOmCMYYbiACFPygd+/qRxtSKKMt1Fa2
rIiTSo8u8MARzwPXHGCMc9fpWvp+qXbW8swiJwxjmcFuo6fMQT39jk/SsZri1eOVWCRkDaJNxXkZ
9OTnC5PHqRk04QQXNi6RxTNGG+VFJChyMnPykdcDHB470TV42YGp5sD2iDdH/o6fNJu2tlQAVwR0
+f1HOfY1sxabbXVk6m33TAIyx5A3j+8OT23d/wA+p5HTbqVLr7VIY7fymVY0ZcoxHPJyD7+36Gaa
9geWOSKIoARIAr859vUZwfl64JPUbXFJb6gdJHpK2RW81EIQ+S8IVQQeDndxzwOAfpmmWFvplzCG
S7+yhsl4nXYwU4GzOcEDv1965u+OoG13FneKeQvHuk3LlX+8Qx5PODjHftUVvBLBefMZowj7ZUJw
S24bV69Sfp+Yq/dSuloI9G025t98lmkjPNGAWdv+WgwBuHqOlaNZ2kQoLOOdliN06ASyK24scDq2
M9McVae9tY22yXEaHJHzNjp161vHRK4ieql9ZrdQuVCifYVSQjlc/wD6qW01C2vjKLeTeI22lh0P
0PfpVqnowOWeK9laW1DxK0se0rcJlmJH3ge2AG56dOKWJ7hbZpJDbNAjgxjOGbA5DcHnBY9cAqOo
q/qVyk+ofYBIQwj3OoDH3BwMZ6e/UVk2pu3leeEMHCskKAjLAvtA2nOFG3J5z9a4pS5W4b/8ErzJ
bC6lt7ySSdGlaf8A1SRr8235j0PLduT+FapUs2+9tgisi9fmAPOQT26454q1p7xtC0aTJK0LmN9o
ICkfwjPpxTr2fyYDhwjH+I/wju34D8PWnLCQs5PcOZlMG1lkAMOzzP8AVyY2+Yevykc57/qMirEP
mpdJGJndMEsrc4GPXr1/rUA3Rsk0sbtncE+8WU56YPr68Vagt5RP58rICU27EHTvye/5DrWdGnON
X3bqPmNtWLVFFFeiQFFFFABRRRQAVW1Cxi1KwltJs7JB1HVT1BHuDg1ZooA4i+8VXsMMtqITHLE2
2WUcYxnOOCOvfHQgjrxjPNfxtvklIlUCIKHJLKSQynjAGQeD+VavirUYheCNLt4rmKQ5CfwLgjIx
3Of1NZ2meHb69gxbMBEHCMxO3AwGOSCd3IH6fhhLmcrDIA1vd3lvHBbpKIpm2R7RtLNzzwMgY79P
pVgjUHiLy23nLLFuEiqNwG8NkkckZAHrzgdK6OXwmlraBrJy11Ev7tjgFu20k5G3HUY/nWjpukQp
D5l1bA3DjEvmBWyeSTkDnO49aXs5aILnB4ubWOVEtFCTOo+b7gBY8dcgZI55Oeh5NNudNvbYM7W7
uxCtsZSuBtzge+B+hGOK9RighgTZFFHGuc4RQBVdbRxqr3bMCpTavPIHHGMdM5Prz6Vfs9APP4Zz
deRaFEmV90Yj81l2s/QcHAxg9QM/qNeytbe1uXOq/ZfKtzuO5lHPUHAPzZwOMnnHXNbeo+HLa8kk
uICYLlsfMgABIPfj/JANYR0uV5104yzSTKyiQqRtRTn+9jcdgAyAB65NQocrC5V1HVZhctDp1yLa
KaUcRzbjJyuMH+Hg5JH05wabLqsV1LGFvQ6qqRq2CGlcD5mIPAY469wcc1em8JC0eIJbxTxtIFBV
WyucknncAOByc9O3SqUulRx6y1tdtEAkBAaMZ+YDcABs6cgADJ96OWTvFgS20t1Ymd7K4ZWbs4GG
O709D9BjPboeps9cs57VJLi4ggfJVlaTgH0ycf5z6ViLoN3C9xcFYpGWHaN+/axKkkADnGTjPfng
VgO3nxOv2HlnG+4WQ4bdkFgnCjHPUjv74UHKGktg3Ol1bVkS7EkYilQA/Ked3ykjqcZPXtwv4Cnu
d7F3+0rayGUhC0nlbcEr8uOB15GT0PasqS4Yr86gzQjBz83msTycdCeQMfStCBVeC4heOVLN4htn
EbgffJA6524AHr9cZrOzk+bqMu6ffTadbtf3q7FmuWUBlIIBZi5Cjp0HXOdue9ZsniCea/hvvKeR
4GbZCsh+YtnA4GOFwM4OSevetOK8+wWLySKtxaL8kkUbcRkliGGRnB6HPOT6dHT6RYy3aT6XfxxT
s+8BVDAv65A/Q5re7aTW4izY+KLcxww3qXEdz5Qdj5DEEf3uBwCOemK345Y5V3Rurj1U57Z/kRXn
F7Dq+mQ+Xf27PCm0faC5Kr8xIGQeB1HqNx6ZFb8X2O20291nSneJ5CpZ50PyruBKqp/L8K0TfUR1
VFYlt4khuJyps7qKFUDSTSINqk4wOCeeenBH54v2eq2d88iQTqzRvsKk4JO3d069P5H0ppp7AXKK
KKYBRRRQAVS1LVbPS7d5Lm4jRgpZUZvmb6DqecdKu1wniXw9Pc6p/a1yweDzNrREFtsa4A6Hvyeo
5PrSbsrgHh/Qhe3cl/q0UrXFxiWGROUB65yMjOegPHseK238Q6XpmnOYpZJjGSBEyFGyMcYKjA59
MVjx3moaxIunW1x9nj8tQu0ADAJwcgHrsbgY/LippvBsrWW7zUkvgwxLyWIPBySR2AOcevXrUJ31
SGNk8aMoE8SiQv8AKtsB3yOQ2QW4yencVuLrMkul2t9BD5qyZDqFPBwTnOeF4PJ9R61xNz4aubC4
330TtaSAKDG27HoCeqnO3sRgV2Phs3EUL2kmnNaxx8q2Ww3YfeOe1CbegEU3i6xMCPAX3Fwrbk4B
BG5c55OMnjNWz4jsVUs+9VwWDNt2kAkEg5wRx19x3NQa14Zj1NpJoZfJnZT1UFS2ODjsff8AwrEf
wzdWcqJFCbk+R3Y+WpGAByevGenoB0obmgNOfXry7kVLK2ljCuqsGC73JPQc4HHc8YOc9Mw3GnTW
MkQsLGZX8v8AfsuCm7ao3Ak/e69ucdD3prb6nYzW32yQW8W4NK4mCM3+yuOW6j5fu9ucZMeqa1du
BNayCW0cRgRyzAAj/aI453c89vas76PnA6e01iBbK3N7L5c7pyGUjcQM8cc8c8VVN5pcCef5jXYS
XbErbf3Z6/KTjPKnkknOak0hYL7RWfzG2Px5hYFgBzgnGOCT2xj1zk8r/ZF8bwrbCIgJyikSAZfO
ORhRjg56gEjrim3KydtQOnh8WWM1v5oVkxyQ7qOM4ODnnH8uuKhvZtNF28l1ZjzlCzoYXw+1VYAk
5UYwCMAkc1hyQX0mryWhKM8abXEZLcAZztPJOT7DoKkuZrWMxyzvDCg/fP5S7DzypADfMOmM+3J6
VEqk07DsXtv2YrczxxzAJ5gKMzjYPvfNnjBYnJGOaydO1Ei91K2e6W3jQKttZsxjVssCCAx4OB0H
XOe/MMlzJdRK8cOWhyglhAQEHCgDPLMdvqeDWjZaLHrUJjktyFjlYCZiDjoR785xjpwOnQlJtR5X
uDCZpxZuiQxoAXjYPGMMxIyCccdT1H8PQVat/EVhaQW8s2nbpD8iS24Rtx5BOCQRyp9friszRmVr
uewmQwTWzj91JggtvA3Y78Hrx146101nc/ZpkSSCbztpRo4uVBzuz0AA5457gVNOXJJwbsD1K0/i
ixuLhYY5AQEYlJU+WQ8YAP8A31WLrFvDpLpeaYx/eEtd2qyhwm4dcdwMnqOM54q7r0txqF5bW1lY
FtmRLhQJI89s9NvIPofWrEvhoQyTtZI5IRiWlAO9sAhV6d1HJ4+vNbpt6x1ER3uiWl7ZHUNOumMD
BW8vcfLCjr7gDuOwyMdMUdI0GS/afNy9u0MiuCFBO7JBGRg44JxxyfbmHSNQ1VdVk+zxSfZJHM1x
BBEPlxjO0Nk8nggY749a7exexniFxZCIpjYGRcYA4x+lNRTd0BaUbVAJLYGMnqaWiitBBRRRQAUU
UUARJbQRy+YkMavt27goBx6VLRRQAUUUUAFFFFAHO+J0BWIzlHhJxHGUB/eYPJyMbfX2FcrM8q3V
uVgiWGSMtuU84BwWXI+mMd8V2OsWU93dKoBMZTCsoO5DyD7dCOpHfniq8HheNsG7CyjduaNnLByS
cknAOcHA6iuZxcptW0H0K8V+50aQQRTtFK5ZX2qN2W2so5z97vjPP41o2li02kXSYUtMXCK5JAIJ
AJLAnPA5x2HFc9BAPLhnlZlW2zCscbHDHc3GDuJY9SOOo68V2diYzZxiIuVAx867WH1GBzTp2c99
tAZwl80gvEVlkCxrtZViVNrZXJOR82B0PqAc9QI9SnaS9BspYxD5uOCQx4AydqjauBz9eBnk6+q6
GuqeIZUmWRImwQYxt3/JyCT2yPfH41Y8NaXLYTiNtNWJEDFrmQ5kZuAB19CenHAohTS0C5yAEv2Y
/aYwlqx/dlYtu8cng4GenJ7ZPQA1etbm68P3Rlt7mJxPGSyvglgvQkZG0/j0yck8Do9c0yWcqLDT
Ig9soCPxhk4OxRwB1P5e9UV0S6uppft0M6vINscjgODnIy20jBHr+nFDjJSvECk09xq+pTXEQH2l
SmxlIVkHOBgrn73GT/UV11rp1wIEa4nxOOQEUFVPuSMn3PFWrfT7W1cPDCFcJs3d8f5A59hVmr9j
F6zVwuVre08ud7iQq0zKEyowAoJIH61JcyeTbSSZAKqSCfXtUtHWrjFRXLERlQ6ZbT/OTIrKJIiY
5Cud2BnI6kAY+ue9SaRpX9kwyQrcvNEWygZQCvbqOvb8qvRRRwxLHEioijAVRgCn0RjyxS7Ac015
qEepvKky9fmt58quCeADjjp97oSw4rT0/WI72UwtGYZRyoZgQ/Gfl9fy/Mc1oMu7HzEAHkDHPtVV
9Nt2kWRd8bLIJPkYgZ+nTn6VKjNPe6GXKKKK0EFFFFABRRRQAUUUUAFFFFABRRRQBBPZwXGN6AEE
HcvDce/WpUjSJAkahVHQAYFOopWW4BRRRTAKKKKACiiigAooooAKKKKACiiigAooooAKKKKACiii
gAooooAKKKKACiiigAooooAKKKKACiiigAooooAKKKKACiiigAooooAKKKKAP//Z</Data></Thumbnail></Binary><mdDateSt Sync="TRUE">20130824</mdDateSt><dataIdInfo><idAbs>&lt;DIV STYLE="text-align:Left;"&gt;&lt;DIV&gt;&lt;DIV&gt;&lt;P STYLE="margin:0 0 0 0;"&gt;&lt;SPAN&gt;The data set contains geographic boundaries of electoral districts, aggregated results of voting,&lt;/SPAN&gt;&lt;/P&gt;&lt;P STYLE="margin:0 0 0 0;"&gt;&lt;SPAN&gt;&lt;SPAN&gt;turnout figures.&lt;/SPAN&gt;&lt;/SPAN&gt;&lt;/P&gt;&lt;P&gt;&lt;SPAN /&gt;&lt;/P&gt;&lt;/DIV&gt;&lt;/DIV&gt;&lt;/DIV&gt;</idAbs><idCredit>The data was prepared by the Caucasus Research Resources Centers Georgia (CRRC Georgia)
for the National Democratic Institute (NDI)
Contact person: David Sichinava;
david@crrccenters.org</idCredit><idCitation><resTitle>Precinct level results of 2010 local elections in the</resTitle><presForm><PresFormCd value="005"></PresFormCd></presForm></idCitation><searchKeys><keyword>Georgia</keyword><keyword>Local elections</keyword><keyword>Results</keyword></searchKeys><resConst><Consts><useLimit>Shape file is distributed freely however, please credit both National Democratic Institute and
Caucasus Research Resources Center when using the data set.</useLimit></Consts></resConst><envirDesc Sync="TRUE">Microsoft Windows Server 2008 R2 Version 6.1 (Build 7601) Service Pack 1; ESRI ArcGIS 10.0.0.2414</envirDesc><dataLang><languageCode value="eng" country="USA"></languageCode></dataLang><descKeys><thesaName uuidref="723f6998-058e-11dc-8314-0800200c9a66"></thesaName><keyword Sync="TRUE">002</keyword></descKeys><spatRpType><SpatRepTypCd value="001"></SpatRepTypCd></spatRpType></dataIdInfo><mdLang><languageCode value="eng"></languageCode></mdLang><distInfo><distFormat><formatName Sync="TRUE">Shapefile</formatName></distFormat><distTranOps><transSize Sync="TRUE">0.000</transSize></distTranOps></distInfo><mdHrLv><ScopeCd value="005"></ScopeCd></mdHrLv><mdHrLvName Sync="TRUE">dataset</mdHrLvName><refSysInfo><RefSystem><refSysID><identCode code="0"></identCode></refSysID></RefSystem></refSysInfo><spdoinfo><ptvctinf><esriterm Name="pres_2013_precincts"><efeatyp Sync="TRUE">Simple</efeatyp><efeageom Sync="TRUE">4</efeageom><esritopo Sync="TRUE">FALSE</esritopo><efeacnt Sync="TRUE">0</efeacnt><spindex Sync="TRUE">FALSE</spindex><linrefer Sync="TRUE">FALSE</linrefer></esriterm></ptvctinf></spdoinfo><spatRepInfo><VectSpatRep><topLvl><TopoLevCd value="001"></TopoLevCd></topLvl><geometObjs><geoObjTyp><GeoObjTypCd value="002"></GeoObjTypCd><geoObjCnt Sync="TRUE">0</geoObjCnt></geoObjTyp></geometObjs></VectSpatRep></spatRepInfo><eainfo><detailed Name="pres_2013_precincts"><enttyp><enttypl Sync="TRUE">pres_2013_precincts</enttypl><enttypt Sync="TRUE">Feature Class</enttypt><enttypc Sync="TRUE">0</enttypc></enttyp><attr><attrlabl Sync="TRUE">FID</attrlabl><attalias Sync="TRUE">FID</attalias><attrtype Sync="TRUE">OID</attrtype><attwidth Sync="TRUE">4</attwidth><atprecis Sync="TRUE">0</atprecis><attscale Sync="TRUE">0</attscale><attrdef Sync="TRUE">Internal feature number.</attrdef><attrdefs Sync="TRUE">ESRI</attrdefs><attrdomv><udom Sync="TRUE">Sequential unique whole numbers that are automatically generated.</udom></attrdomv></attr><attr><attrlabl Sync="TRUE">Shape</attrlabl><attalias Sync="TRUE">Shape</attalias><attrtype Sync="TRUE">Geometry</attrtype><attwidth Sync="TRUE">0</attwidth><atprecis Sync="TRUE">0</atprecis><attscale Sync="TRUE">0</attscale><attrdef Sync="TRUE">Feature geometry.</attrdef><attrdefs Sync="TRUE">ESRI</attrdefs><attrdomv><udom Sync="TRUE">Coordinates defining the features.</udom></attrdomv></attr><attr><attrlabl Sync="TRUE">Shape_Leng</attrlabl><attalias Sync="TRUE">Shape_Leng</attalias><attrtype Sync="TRUE">Double</attrtype><attwidth Sync="TRUE">19</attwidth><atprecis Sync="TRUE">0</atprecis><attscale Sync="TRUE">0</attscale></attr><attr><attrlabl Sync="TRUE">Shape_Area</attrlabl><attalias Sync="TRUE">Shape_Area</attalias><attrtype Sync="TRUE">Double</attrtype><attwidth Sync="TRUE">19</attwidth><atprecis Sync="TRUE">0</atprecis><attscale Sync="TRUE">0</attscale><attrdef Sync="TRUE">Area of feature in internal units squared.</attrdef><attrdefs Sync="TRUE">ESRI</attrdefs><attrdomv><udom Sync="TRUE">Positive real numbers that are automatically generated.</udom></attrdomv></attr><attr><attrlabl Sync="TRUE">District</attrlabl><attalias Sync="TRUE">District</attalias><attrtype Sync="TRUE">Integer</attrtype><attwidth Sync="TRUE">9</attwidth><atprecis Sync="TRUE">9</atprecis><attscale Sync="TRUE">0</attscale></attr><attr><attrlabl Sync="TRUE">Precinct</attrlabl><attalias Sync="TRUE">Precinct</attalias><attrtype Sync="TRUE">Integer</attrtype><attwidth Sync="TRUE">9</attwidth><atprecis Sync="TRUE">9</atprecis><attscale Sync="TRUE">0</attscale></attr><attr><attrlabl Sync="TRUE">PrecID</attrlabl><attalias Sync="TRUE">PrecID</attalias><attrtype Sync="TRUE">Single</attrtype><attwidth Sync="TRUE">13</attwidth><atprecis Sync="TRUE">0</atprecis><attscale Sync="TRUE">0</attscale></attr></detailed></eainfo></metadata>
